aio_mpv_jsonipc/MPV.py
aio_mpv_jsonipc/__init__.py
aio_mpv_jsonipc-1.0.dist-info/LICENSE
aio_mpv_jsonipc-1.0.dist-info/METADATA
aio_mpv_jsonipc-1.0.dist-info/WHEEL
aio_mpv_jsonipc-1.0.dist-info/top_level.txt
aio_mpv_jsonipc-1.0.dist-info/RECORD
